sanic_skywalking_middleware.py
sanic_skywalking_middleware-1.0.1.dist-info/LICENSE
sanic_skywalking_middleware-1.0.1.dist-info/METADATA
sanic_skywalking_middleware-1.0.1.dist-info/WHEEL
sanic_skywalking_middleware-1.0.1.dist-info/top_level.txt
sanic_skywalking_middleware-1.0.1.dist-info/RECORD
