Metadata-Version: 2.1
Name: sanic-skywalking-middleware
Version: 1.0.1
Summary: A SkyWalking Agent/Middleware for Sanic Framework.
Home-page: https://github.com/sungitly/wsgi-skywalking-middleware
Author: Lei Sun
Author-email: leix.sun@qq.com
License: MIT
Download-URL: https://github.com/sungitly/wsgi-skywalking-middleware/archive/v1.0.1.tar.gz
Keywords: sanic,skywalking,middleware
Platform: UNKNOWN
Requires-Dist: sanic (>=20.6.1)
Requires-Dist: apache-skywalking (==0.1.0)
